{"coord":{"lon":106.8451,"lat":-6.2146},"weather":[{"id":804,"main":"Clouds","description":"overcast clouds","icon":"04d"}],"base":"stations","main":{"temp":33.3,"feels_like":39.92,"temp_min":31.61,"temp_max":33.38,"pressure":1005,"humidity":59,"sea_level":1005,"grnd_level":1003},"visibility":10000,"wind":{"speed":4.95,"deg":18,"gust":3.73},"clouds":{"all":90},"dt":1747128440,"sys":{"type":2,"id":2073276,"country":"ID","sunrise":1747090427,"sunset":1747133056},"timezone":25200,"id":1642911,"name":"Jakarta","cod":200}